line_planner/__init__.py
line_planner/_version.py
line_planner/main.py
line_planner/api/__init__.py
line_planner/api/stdin_processor.py
line_planner/core/__init__.py
line_planner/core/standalone.py
line_planner-1.1.6.dist-info/licenses/LICENSE
line_planner-1.1.6.dist-info/METADATA
line_planner-1.1.6.dist-info/WHEEL
line_planner-1.1.6.dist-info/top_level.txt
line_planner-1.1.6.dist-info/RECORD
