Metadata-Version: 2.4
Name: line-planner
Version: 1.1.6
Summary: SIF航线规划器 - 基于v1.1.0简化版本，专注稳定性和性能
Author-email: WayPoint Planning Team <waypoint@example.com>
Maintainer-email: WayPoint Planning Team <waypoint@example.com>
License-Expression: MIT
Project-URL: Homepage, https://github.com/1034378361/WayPointPlanning3
Project-URL: Documentation, https://github.com/1034378361/WayPointPlanning3/blob/main/CLAUDE.md
Project-URL: Repository, https://github.com/1034378361/WayPointPlanning3.git
Project-URL: Bug Tracker, https://github.com/1034378361/WayPointPlanning3/issues
Project-URL: Changelog, https://github.com/1034378361/WayPointPlanning3/commits
Keywords: flight planning,waypoint,drone,UAV,KML,path planning,GIS
Classifier: Development Status :: 5 - Production/Stable
Classifier: Intended Audience :: Science/Research
Classifier: Topic :: Scientific/Engineering :: GIS
Classifier: Programming Language :: Python :: 3
Classifier: Programming Language :: Python :: 3.8
Classifier: Programming Language :: Python :: 3.9
Classifier: Programming Language :: Python :: 3.10
Classifier: Programming Language :: Python :: 3.11
Classifier: Programming Language :: Python :: 3.12
Classifier: Operating System :: OS Independent
Requires-Python: >=3.8
License-File: LICENSE
Requires-Dist: numpy>=1.21.0
Requires-Dist: matplotlib>=3.5.0
Requires-Dist: requests>=2.25.0
Provides-Extra: dev
Requires-Dist: pytest>=6.0; extra == "dev"
Requires-Dist: pytest-cov>=2.0; extra == "dev"
Requires-Dist: black>=22.0; extra == "dev"
Requires-Dist: isort>=5.0; extra == "dev"
Requires-Dist: flake8>=4.0; extra == "dev"
Requires-Dist: mypy>=0.900; extra == "dev"
Provides-Extra: docs
Requires-Dist: sphinx>=4.0; extra == "docs"
Requires-Dist: sphinx-rtd-theme>=1.0; extra == "docs"
Provides-Extra: test
Requires-Dist: pytest>=6.0; extra == "test"
Requires-Dist: pytest-cov>=2.0; extra == "test"
Requires-Dist: pytest-mock>=3.0; extra == "test"
Dynamic: license-file
